fastgrpcio/__init__.py
fastgrpcio/_utils.py
fastgrpcio/context.py
fastgrpcio/exceptions.py
fastgrpcio/fast_grpc.py
fastgrpcio/grpc_compiler.py
fastgrpcio/middlewares.py
fastgrpcio/mixins.py
fastgrpcio/schemas.py
fastgrpcio/calls/__init__.py
fastgrpcio/tracing/__init__.py
fastgrpcio/tracing/middleware.py
fastgrpcio-0.1.2.dist-info/licenses/LICENSE
fastgrpcio-0.1.2.dist-info/METADATA
fastgrpcio-0.1.2.dist-info/WHEEL
fastgrpcio-0.1.2.dist-info/top_level.txt
fastgrpcio-0.1.2.dist-info/RECORD
