Metadata-Version: 2.4
Name: fastgrpcio
Version: 0.1.2
Summary: Rapid fast development of gRPC services with Pydantic models
Author-email: Sergey Brusnov <sergey.brusnov1900@gmail.com>
License: MIT
Requires-Python: >=3.11
License-File: LICENSE
Requires-Dist: fast-depends>=2.4.12
Requires-Dist: grpcio>=1.75.1
Requires-Dist: grpcio-reflection>=1.75.1
Requires-Dist: grpcio-status>=1.75.1
Requires-Dist: grpcio-tools>=1.75.1
Requires-Dist: pydantic>=2.12.0
Dynamic: license-file
